mkfile/__version__.py
mkfile/mkfile.pyx
mkfile/mkfile.cpython-311-i386-linux-musl.so
mkfile/__main__.py
mkfile/mkfile.jpg
mkfile/__init__.py
mkfile-1.0.12.dist-info/LICENSE
mkfile-1.0.12.dist-info/WHEEL
mkfile-1.0.12.dist-info/entry_points.txt
mkfile-1.0.12.dist-info/top_level.txt
mkfile-1.0.12.dist-info/METADATA
mkfile-1.0.12.dist-info/RECORD
