Metadata-Version: 2.1
Name: mkfile
Version: 1.0.12
Summary: Advanced file creator with brace expansion and notification support
Home-page: https://github.com/cumulus13/mkfile
Author: cumulus13
Author-email: cumulus13@gmail.com
Project-URL: Bug Reports, https://github.com/cumulus13/mkfile/issues
Project-URL: Source, https://github.com/cumulus13/mkfile
Keywords: file creation,command-line,brace expansion,developer tools
Classifier: Development Status :: 5 - Production/Stable
Classifier: Intended Audience :: Developers
Classifier: Topic :: Software Development :: Build Tools
Classifier: Topic :: System :: Filesystems
Classifier: License :: OSI Approved :: MIT License
Classifier: Programming Language :: Python :: 3
Classifier: Programming Language :: Python :: 3.6
Classifier: Programming Language :: Python :: 3.7
Classifier: Programming Language :: Python :: 3.8
Classifier: Programming Language :: Python :: 3.9
Classifier: Programming Language :: Python :: 3.10
Classifier: Programming Language :: Python :: 3.11
Classifier: Operating System :: OS Independent
Classifier: Environment :: Console
Requires-Python: >=3.6
License-File: LICENSE
Provides-Extra: clipboard
Requires-Dist: clipboard >=0.0.4 ; extra == 'clipboard'
Provides-Extra: full
Requires-Dist: gntp >=1.0.3 ; extra == 'full'
Requires-Dist: clipboard >=0.0.4 ; extra == 'full'
Requires-Dist: licface ; extra == 'full'
Provides-Extra: licface
Requires-Dist: licface ; extra == 'licface'
Provides-Extra: notifications
Requires-Dist: gntp >=1.0.3 ; extra == 'notifications'
